{
  "users_left": [
    {
      "avatar": "https://storage.googleapis.com/labspoon-prod-284615.appspot.com/users/mq2FIrsbWeQjXcTl16Nstj4gv9o2/avatar",
      "name": "Patrick Leask",
      "url": "https://labspoon-prod-284615.web.app/user/mq2FIrsbWeQjXcTl16Nstj4gv9o2"
    },
    {
      "avatar": "https://storage.googleapis.com/labspoon-prod-284615.appspot.com/users/mq2FIrsbWeQjXcTl16Nstj4gv9o2/avatar",
      "name": "Patrick Leask",
      "url": "https://labspoon-prod-284615.web.app/user/mq2FIrsbWeQjXcTl16Nstj4gv9o2"
    }
  ],
  "users_right": [
    {
      "avatar": "https://storage.googleapis.com/labspoon-prod-284615.appspot.com/users/mq2FIrsbWeQjXcTl16Nstj4gv9o2/avatar",
      "name": "Patrick Leask",
      "url": "https://labspoon-prod-284615.web.app/user/mq2FIrsbWeQjXcTl16Nstj4gv9o2"
    }
  ],
  "topics_left": [
    {
      "name": "Plastic Waste",
      "url": "https://labspoon-prod-284615.web.app/topic/Z2Uh47QrdBtEdwh714mj"
    },
    {
      "name": "Plastic Waste",
      "url": "https://labspoon-prod-284615.web.app/topic/Z2Uh47QrdBtEdwh714mj"
    }
  ],
  "topics_right": [
    {
      "name": "Plastic Waste",
      "url": "https://labspoon-prod-284615.web.app/topic/Z2Uh47QrdBtEdwh714mj"
    }
  ]
}
